odoo/addons/l10n_es_atc_mod415/README.rst
odoo/addons/l10n_es_atc_mod415/__init__.py
odoo/addons/l10n_es_atc_mod415/__manifest__.py
odoo/addons/l10n_es_atc_mod415/data/l10n.es.aeat.map.tax.csv
odoo/addons/l10n_es_atc_mod415/data/l10n.es.aeat.map.tax.line.csv
odoo/addons/l10n_es_atc_mod415/data/l10n.es.aeat.map.tax.line.tax.csv
odoo/addons/l10n_es_atc_mod415/data/mail_template_data.xml
odoo/addons/l10n_es_atc_mod415/i18n/es.po
odoo/addons/l10n_es_atc_mod415/i18n/l10n_es_atc_mod415.pot
odoo/addons/l10n_es_atc_mod415/models/__init__.py
odoo/addons/l10n_es_atc_mod415/models/account_move.py
odoo/addons/l10n_es_atc_mod415/models/mod415.py
odoo/addons/l10n_es_atc_mod415/models/res_partner.py
odoo/addons/l10n_es_atc_mod415/readme/CONTRIBUTORS.md
odoo/addons/l10n_es_atc_mod415/readme/DESCRIPTION.md
odoo/addons/l10n_es_atc_mod415/readme/INSTALL.md
odoo/addons/l10n_es_atc_mod415/security/ir.model.access.csv
odoo/addons/l10n_es_atc_mod415/security/mod_415_security.xml
odoo/addons/l10n_es_atc_mod415/static/description/icon.png
odoo/addons/l10n_es_atc_mod415/static/description/index.html
odoo/addons/l10n_es_atc_mod415/tests/__init__.py
odoo/addons/l10n_es_atc_mod415/tests/test_l10n_es_atc_mod415.py
odoo/addons/l10n_es_atc_mod415/views/account_move_view.xml
odoo/addons/l10n_es_atc_mod415/views/mod415_templates.xml
odoo/addons/l10n_es_atc_mod415/views/mod415_view.xml
odoo/addons/l10n_es_atc_mod415/views/report_415_partner.xml
odoo/addons/l10n_es_atc_mod415/views/res_partner_view.xml
odoo_addon_l10n_es_atc_mod415-17.0.1.0.0.2.dist-info/METADATA
odoo_addon_l10n_es_atc_mod415-17.0.1.0.0.2.dist-info/WHEEL
odoo_addon_l10n_es_atc_mod415-17.0.1.0.0.2.dist-info/top_level.txt
odoo_addon_l10n_es_atc_mod415-17.0.1.0.0.2.dist-info/RECORD
